hu_names.py
hu_names-1.0.0.dist-info/METADATA
hu_names-1.0.0.dist-info/WHEEL
hu_names-1.0.0.dist-info/top_level.txt
hu_names-1.0.0.dist-info/RECORD
