Metadata-Version: 2.1
Name: hu-names
Version: 1.0.0
Summary: Hungarian first and second names
Home-page: https://github.com/kobanya
Author: Nagy Béla
Author-email: nagy.belabudapest@gmail.com
Classifier: License :: OSI Approved :: MIT License
Classifier: Programming Language :: Python :: 3
Classifier: Programming Language :: Python :: 3.6
Classifier: Programming Language :: Python :: 3.7
Classifier: Programming Language :: Python :: 3.8
Classifier: Programming Language :: Python :: 3.9
